MANIFEST.in
README.rst
buildout.cfg
requirements.txt
setup.py
version.txt
bob/__init__.py
bob.db.casia_fasd.egg-info/PKG-INFO
bob.db.casia_fasd.egg-info/SOURCES.txt
bob.db.casia_fasd.egg-info/dependency_links.txt
bob.db.casia_fasd.egg-info/entry_points.txt
bob.db.casia_fasd.egg-info/not-zip-safe
bob.db.casia_fasd.egg-info/requires.txt
bob.db.casia_fasd.egg-info/top_level.txt
bob/db/__init__.py
bob/db/casia_fasd/__init__.py
bob/db/casia_fasd/driver.py
bob/db/casia_fasd/models.py
bob/db/casia_fasd/spoofing.py
bob/db/casia_fasd/test.py
bob/db/casia_fasd/face-locations/test_release/1/1.face
bob/db/casia_fasd/face-locations/test_release/1/2.face
bob/db/casia_fasd/face-locations/test_release/1/3.face
bob/db/casia_fasd/face-locations/test_release/1/4.face
bob/db/casia_fasd/face-locations/test_release/1/5.face
bob/db/casia_fasd/face-locations/test_release/1/6.face
bob/db/casia_fasd/face-locations/test_release/1/7.face
bob/db/casia_fasd/face-locations/test_release/1/8.face
bob/db/casia_fasd/face-locations/test_release/1/HR_1.face
bob/db/casia_fasd/face-locations/test_release/1/HR_2.face
bob/db/casia_fasd/face-locations/test_release/1/HR_3.face
bob/db/casia_fasd/face-locations/test_release/1/HR_4.face
bob/db/casia_fasd/face-locations/test_release/10/1.face
bob/db/casia_fasd/face-locations/test_release/10/2.face
bob/db/casia_fasd/face-locations/test_release/10/3.face
bob/db/casia_fasd/face-locations/test_release/10/4.face
bob/db/casia_fasd/face-locations/test_release/10/5.face
bob/db/casia_fasd/face-locations/test_release/10/6.face
bob/db/casia_fasd/face-locations/test_release/10/7.face
bob/db/casia_fasd/face-locations/test_release/10/8.face
bob/db/casia_fasd/face-locations/test_release/10/HR_1.face
bob/db/casia_fasd/face-locations/test_release/10/HR_2.face
bob/db/casia_fasd/face-locations/test_release/10/HR_3.face
bob/db/casia_fasd/face-locations/test_release/10/HR_4.face
bob/db/casia_fasd/face-locations/test_release/11/1.face
bob/db/casia_fasd/face-locations/test_release/11/2.face
bob/db/casia_fasd/face-locations/test_release/11/3.face
bob/db/casia_fasd/face-locations/test_release/11/4.face
bob/db/casia_fasd/face-locations/test_release/11/5.face
bob/db/casia_fasd/face-locations/test_release/11/6.face
bob/db/casia_fasd/face-locations/test_release/11/7.face
