Metadata-Version: 1.1
Name: bob.db.casia-fasd
Version: 2.0.10
Summary: CASIA Face Anti-Spoofing Database Access API for Bob
Home-page: http://pypi.python.org/pypi/bob.db.casia_fasd
Author: Andre Anjos, Ivana Chingovska
Author-email: andre.anjos@idiap.ch, ivana.chingovska@idiap.ch
License: BSD
Platform: UNKNOWN
Classifier: Framework :: Bob
Classifier: Development Status :: 4 - Beta
Classifier: Intended Audience :: Science/Research
Classifier: License :: OSI Approved :: BSD License
Classifier: Natural Language :: English
Classifier: Programming Language :: Python
Classifier: Programming Language :: Python :: 3
Classifier: Topic :: Scientific/Engineering :: Artificial Intelligence
Classifier: Topic :: Database :: Front-Ends
